{
   "categorias": [
      { "id": "1","value": "BERMUDA"},
      { "id": "2","value": "BOLSA"  },
      { "id": "3","value": "CALÇA"  },
      { "id": "4","value": "CALÇADO"},
      { "id": "5","value": "CAMISA" },
      { "id": "6","value": "CAMISA DE TIME"  },
      { "id": "7","value": "CASACO"  },
      { "id": "8","value": "COPA DO MUNDO"  },
      { "id": "9","value": "JEANS"  },
      { "id": "10","value": "JÓIA"  },
      { "id": "11","value": "LONG"  },
      { "id": "12","value": "NIKE"  },
      { "id": "13","value": "ÓCULOS"}
   ],
   "produtos": [
      {
         "id": 1,
         "nome": "Chef Hat 20cm",
         "categorias": [
            "NIKE",
            "JÓIA",
            "ÓCULOS",
            "BOLSA"
         ],
         "produtos": 5,
         "unidades": 37
      },
      {
         "id": 2,
         "nome": "Wine - Sherry Dry Sack, William",
         "categorias": [
            "LONG"
         ],
         "produtos": 4,
         "unidades": 23
      },
      {
         "id": 3,
         "nome": "Salad Dressing",
         "categorias": [
            "CAMISA"
         ],
         "produtos": 5,
         "unidades": 38
      },
      {
         "id": 4,
         "nome": "Trueblue - Blueberry",
         "categorias": [
            "BOLSA",
            "JÓIA"
         ],
         "produtos": 9,
         "unidades": 17
      },
      {
         "id": 5,
         "nome": "Cucumber - English",
         "categorias": [
            "CAMISA DE TIME",
            "CASACO"
         ],
         "produtos": 6,
         "unidades": 37
      },
      {
         "id": 6,
         "nome": "Octopus - Baby, Cleaned",
         "categorias": [
            "BOLSA",
            "JÓIA"
         ],
         "produtos": 4,
         "unidades": 16
      },
      {
         "id": 7,
         "nome": "Tomatoes - Heirloom",
         "categorias": [
            "ÓCULOS"
         ],
         "produtos": 5,
         "unidades": 22
      },
      {
         "id": 8,
         "nome": "Sage Derby",
         "categorias": [
            "LONG",
            "COPA DO MUNDO",
            "JÓIA"
         ],
         "produtos": 9,
         "unidades": 23
      },
      {
         "id": 9,
         "nome": "Apricots - Halves",
         "categorias": [
            "COPA DO MUNDO"
         ],
         "produtos": 7,
         "unidades": 19
      },
      {
         "id": 10,
         "nome": "Cake - Mini Potato Pancake",
         "categorias": [
            "BOLSA"
         ],
         "produtos": 8,
         "unidades": 24
      },
      {
         "id": 11,
         "nome": "Coffee Cup 8oz 5338cd",
         "categorias": [
            "JÓIA",
            "CALÇADO",
            "CAMISA",
            "ÓCULOS"
         ],
         "produtos": 8,
         "unidades": 26
      },
      {
         "id": 12,
         "nome": "Cheese Cloth",
         "categorias": [
            "JEANS",
            "ÓCULOS",
            "CALÇADO",
            "NIKE"
         ],
         "produtos": 5,
         "unidades": 27
      },
      {
         "id": 13,
         "nome": "Appetizer - Seafood Assortment",
         "categorias": [
            "CALÇA",
            "ÓCULOS",
            "BOLSA"
         ],
         "produtos": 10,
         "unidades": 36
      },
      {
         "id": 14,
         "nome": "Corn Syrup",
         "categorias": [
            "ÓCULOS"
         ],
         "produtos": 7,
         "unidades": 1
      },
      {
         "id": 15,
         "nome": "Chinese Foods - Chicken",
         "categorias": [
            "BOLSA",
            "CALÇADO",
            "COPA DO MUNDO",
            "JÓIA"
         ],
         "produtos": 3,
         "unidades": 14
      },
      {
         "id": 16,
         "nome": "Kellogs Cereal In A Cup",
         "categorias": [
            "CASACO",
            "ÓCULOS",
            "COPA DO MUNDO",
            "BERMUDA"
         ],
         "produtos": 1,
         "unidades": 18
      },
      {
         "id": 17,
         "nome": "Lychee - Canned",
         "categorias": [
            "CASACO",
            "CAMISA DE TIME"
         ],
         "produtos": 1,
         "unidades": 25
      },
      {
         "id": 18,
         "nome": "Beef - Diced",
         "categorias": [
            "BOLSA",
            "JEANS"
         ],
         "produtos": 7,
         "unidades": 21
      },
      {
         "id": 19,
         "nome": "Huck Towels White",
         "categorias": [
            "ÓCULOS",
            "NIKE"
         ],
         "produtos": 9,
         "unidades": 10
      },
      {
         "id": 20,
         "nome": "Bamboo Shoots - Sliced",
         "categorias": [
            "BOLSA",
            "CALÇA"
         ],
         "produtos": 5,
         "unidades": 40
      },
      {
         "id": 21,
         "nome": "Pomegranates",
         "categorias": [
            "CAMISA"
         ],
         "produtos": 5,
         "unidades": 27
      },
      {
         "id": 22,
         "nome": "Everfresh Products",
         "categorias": [
            "NIKE",
            "ÓCULOS"
         ],
         "produtos": 6,
         "unidades": 29
      },
      {
         "id": 23,
         "nome": "Oil - Peanut",
         "categorias": [
            "CAMISA DE TIME",
            "CALÇA",
            "CALÇADO"
         ],
         "produtos": 5,
         "unidades": 12
      },
      {
         "id": 24,
         "nome": "Island Oasis - Pina Colada",
         "categorias": [
            "LONG",
            "CALÇA"
         ],
         "produtos": 4,
         "unidades": 2
      },
      {
         "id": 25,
         "nome": "Lamb - Shoulder",
         "categorias": [
            "CAMISA",
            "CALÇADO",
            "NIKE"
         ],
         "produtos": 4,
         "unidades": 3
      }
   ]
}